elasticsearch_serverless/__init__.py
elasticsearch_serverless/_otel.py
elasticsearch_serverless/_utils.py
elasticsearch_serverless/_version.py
elasticsearch_serverless/client.py
elasticsearch_serverless/compat.py
elasticsearch_serverless/exceptions.py
elasticsearch_serverless/py.typed
elasticsearch_serverless/serializer.py
elasticsearch_serverless/_async/__init__.py
elasticsearch_serverless/_async/helpers.py
elasticsearch_serverless/_async/client/__init__.py
elasticsearch_serverless/_async/client/_base.py
elasticsearch_serverless/_async/client/async_search.py
elasticsearch_serverless/_async/client/cat.py
elasticsearch_serverless/_async/client/cluster.py
elasticsearch_serverless/_async/client/connector.py
elasticsearch_serverless/_async/client/enrich.py
elasticsearch_serverless/_async/client/eql.py
elasticsearch_serverless/_async/client/esql.py
elasticsearch_serverless/_async/client/graph.py
elasticsearch_serverless/_async/client/indices.py
elasticsearch_serverless/_async/client/inference.py
elasticsearch_serverless/_async/client/ingest.py
elasticsearch_serverless/_async/client/license.py
elasticsearch_serverless/_async/client/logstash.py
elasticsearch_serverless/_async/client/ml.py
elasticsearch_serverless/_async/client/query_rules.py
elasticsearch_serverless/_async/client/search_application.py
elasticsearch_serverless/_async/client/security.py
elasticsearch_serverless/_async/client/sql.py
elasticsearch_serverless/_async/client/synonyms.py
elasticsearch_serverless/_async/client/tasks.py
elasticsearch_serverless/_async/client/transform.py
elasticsearch_serverless/_async/client/utils.py
elasticsearch_serverless/_sync/__init__.py
elasticsearch_serverless/_sync/client/__init__.py
elasticsearch_serverless/_sync/client/_base.py
elasticsearch_serverless/_sync/client/async_search.py
elasticsearch_serverless/_sync/client/cat.py
elasticsearch_serverless/_sync/client/cluster.py
elasticsearch_serverless/_sync/client/connector.py
elasticsearch_serverless/_sync/client/enrich.py
elasticsearch_serverless-0.8.0.20231031.dist-info/METADATA
elasticsearch_serverless-0.8.0.20231031.dist-info/WHEEL
elasticsearch_serverless-0.8.0.20231031.dist-info/licenses/LICENSE
elasticsearch_serverless-0.8.0.20231031.dist-info/licenses/NOTICE
elasticsearch_serverless-0.8.0.20231031.dist-info/RECORD
